setup.py
readfmf/__init__.py
readfmf/readfmf.py
readfmf.egg-info/PKG-INFO
readfmf.egg-info/SOURCES.txt
readfmf.egg-info/dependency_links.txt
readfmf.egg-info/requires.txt
readfmf.egg-info/top_level.txt
readfmf.egg-info/zip-safe
test/test_data.py
test/test_header.py