Metadata-Version: 1.0
Name: readfmf
Version: 0.1.1
Summary: An easy way to read fmf files
Home-page: http://arxiv.org/abs/0904.1299
Author: Rolf Würdemann
Author-email: Rolf.Wuerdemann@fmf.uni-freiburg.de
License: BSD
Platform: UNKNOWN
Classifier: Development Status :: 4 - Beta
Classifier: Topic :: Utilities
Classifier: Environment :: Console
Classifier: License :: OSI Approved :: BSD License
